odoo/addons/mrp_unbuild_subcontracting/README.rst
odoo/addons/mrp_unbuild_subcontracting/__init__.py
odoo/addons/mrp_unbuild_subcontracting/__manifest__.py
odoo/addons/mrp_unbuild_subcontracting/i18n/es.po
odoo/addons/mrp_unbuild_subcontracting/i18n/it.po
odoo/addons/mrp_unbuild_subcontracting/i18n/mrp_unbuild_subcontracting.pot
odoo/addons/mrp_unbuild_subcontracting/models/__init__.py
odoo/addons/mrp_unbuild_subcontracting/models/mrp_unbuild.py
odoo/addons/mrp_unbuild_subcontracting/models/stock_move.py
odoo/addons/mrp_unbuild_subcontracting/models/stock_picking.py
odoo/addons/mrp_unbuild_subcontracting/readme/CONTRIBUTORS.rst
odoo/addons/mrp_unbuild_subcontracting/readme/DESCRIPTION.rst
odoo/addons/mrp_unbuild_subcontracting/static/description/icon.png
odoo/addons/mrp_unbuild_subcontracting/static/description/index.html
odoo/addons/mrp_unbuild_subcontracting/tests/__init__.py
odoo/addons/mrp_unbuild_subcontracting/tests/test_mrp_unbuild_subcontracting.py
odoo/addons/mrp_unbuild_subcontracting/views/mrp_unbuild_views.xml
odoo14_addon_mrp_unbuild_subcontracting-14.0.1.0.2.dist-info/METADATA
odoo14_addon_mrp_unbuild_subcontracting-14.0.1.0.2.dist-info/WHEEL
odoo14_addon_mrp_unbuild_subcontracting-14.0.1.0.2.dist-info/top_level.txt
odoo14_addon_mrp_unbuild_subcontracting-14.0.1.0.2.dist-info/RECORD
